[
  {
    "id": "widget-exists",
    "description": "Widget file exists",
    "cmd": "test -f lib/screens/browse/_widgets/LinkCard.dart",
    "passed": true,
    "exit_code": 0,
    "output": ""
  },
  {
    "id": "dart-valid",
    "description": "Dart analysis passes",
    "cmd": "dart analyze lib/screens/browse/_widgets/LinkCard.dart",
    "passed": true,
    "exit_code": 0,
    "output": "Analyzing LinkCard.dart...\n\n   info - LinkCard.dart:1:1 - The file name 'LinkCard.dart' isn't a lower_case_with_underscores identifier. Try changing the name to follow the lower_case_with_underscores style. - file_names\n\n1 issue found."
  }
]