{
  "taskId": "003-library-02-design",
  "attemptNumber": 1,
  "inputs": [
    {
      "pattern": ".stitch/designs/library/SPEC.md",
      "count": 1,
      "samples": [
        ".stitch/designs/library/SPEC.md"
      ]
    },
    {
      "pattern": ".stitch/system/DESIGN.md",
      "count": 1,
      "samples": [
        ".stitch/system/DESIGN.md"
      ]
    },
    {
      "pattern": ".stitch/system/META.md",
      "count": 1,
      "samples": [
        ".stitch/system/META.md"
      ]
    }
  ],
  "outputs": [
    ".stitch/designs/library/META.md",
    ".stitch/designs/library/design.html"
  ],
  "blocked": false
}